Workbook

Sheet Model
A2: Tata Consultancy Services Ltd - Three-Statement Model (FY22A-FY31E)
A3: ₹ crore unless stated | A = actual, E = estimate | Blue = input, black = formula, yellow = forecast assumption
A5: Particulars | B5: FY22A | C5: FY23A | D5: FY24A | E5: FY25A | F5: FY26A | G5: FY27E | H5: FY28E | I5: FY29E | J5: FY30E | K5: FY31E | L5: Basis for assumption
A8: ASSUMPTIONS
A9: Revenue and profitability
A10: Revenue growth | C10: =C41/B41-1 -> 0.17576687 | D10: =D41/C41-1 -> 0.068460645 | E10: =E41/D41-1 -> 0.059906265 | F10: =F41/E41-1 -> 0.04581238 | G10: 0.05 | H10: 0.055 | I10: 0.06 | J10: 0.06 | K10: 0.06 | L10: TCS grew about 6% a year over the last 3 years, but only 4.6% in FY26. We start a little lower at 5% and slowly go back to 6%.
A11: Cost of revenue (% of revenue) | B11: =B42/B41 -> 0.56696079 | C11: =C42/C41 -> 0.57395612 | D11: =D42/D41 -> 0.59708252 | E11: =E42/E41 -> 0.61661262 | F11: =F42/F41 -> 0.59693058 | G11: 0.6 | H11: 0.6 | I11: 0.6 | J11: 0.6 | K11: 0.6 | L11: Salaries and hardware take about 60% of revenue in most years (59.7% in FY24 and FY26). We keep it at 60%, leaving room for yearly pay hikes.
A12: Other operating expenses (% of revenue) | B12: =B44/B41 -> 0.15634615 | C12: =C44/C41 -> 0.16320556 | D12: =D44/D41 -> 0.13998746 | E12: =E44/E41 -> 0.11938165 | F12: =F44/F41 -> 0.14888717 | G12: 0.13 | H12: 0.13 | I12: 0.13 | J12: 0.13 | K12: 0.13 | L12: All other day-to-day costs are usually 12-14% of revenue once one-off charges are taken out. We use the middle, 13%.
A13: Interest yield (% of opening cash + investments) | C13: =C48/(B67+B65) -> 0.066685829 | D13: =D48/(C67+C65) -> 0.078452122 | E13: =E48/(D67+D65) -> 0.0731664 | F13: =F48/(E67+E65) -> 0.08301204 | G13: 0.075 | H13: 0.075 | I13: 0.075 | J13: 0.075 | K13: 0.075 | L13: TCS earns interest on its cash and investments. It earned 6.7-8.3% a year on the opening balance (about 7.6% on average), so we use 7.5%. More cash now means more interest.
A14: Other non-interest income (% of revenue) | B14: =B49/B41 -> 0.0070663454 | C14: =C49/C41 -> 0.0008915186 | D14: =D49/D41 -> 0.0026609324 | E14: =E49/E41 -> 0.0026084504 | F14: =F49/F41 -> 0.002052273 | G14: 0.002 | H14: 0.002 | I14: 0.002 | J14: 0.002 | K14: 0.002 | L14: Income other than interest (e.g. gains on investments, dividends). Small and volatile about 0.2-0.3% of revenue in FY24-26. We use 0.2%.
A15: Effective tax rate (% of profit before tax) | B15: =B52/B51 -> 0.25611856 | C15: =C52/C51 -> 0.25662924 | D15: =D52/D51 -> 0.25643176 | E15: =E52/E51 -> 0.25308047 | F15: =F52/F51 -> 0.24482722 | G15: 0.255 | H15: 0.255 | I15: 0.255 | J15: 0.255 | K15: 0.255 | L15: TCS has paid 24.5-25.7% of its profit as tax every year. India's company tax rate is about 25%, so we use 25.5%.
A16: Non-controlling interests (% of profit) | B16: =B54/B53 -> 0.0031730344 | C16: =C54/C53 -> 0.0036876817 | D16: =D54/D53 -> 0.0041432569 | E16: =E54/E53 -> 0.0050003074 | F16: =F54/F53 -> 0.0049338779 | G16: 0.005 | H16: 0.005 | I16: 0.005 | J16: 0.005 | K16: 0.005 | L16: A small slice of profit belongs to minority partners in some subsidiaries - about 0.5% recently. We keep 0.5%.
A17: Weighted average shares (crore) | B17: =B56 -> 369.88322 | C17: =C56 -> 365.90514 | D17: =D56 -> 364.68518 | E17: =E56 -> 361.80875 | F17: =F56 -> 361.80875 | G17: 361.80875 | H17: 361.80875 | I17: 361.80875 | J17: 361.80875 | K17: 361.80875 | L17: We assume no new shares and no buy-backs, so the number of shares stays the same as FY26.
A18: Capex, depreciation and amortisation
A19: PP&E capex (% of revenue) | B19: =-B91/B41 -> 0.013027108 | C19: =-C91/C41 -> 0.012175217 | D19: =-D91/D41 -> 0.0092655245 | E19: =-E91/E41 -> 0.011722361 | F19: =-F91/F41 -> 0.014152445 | G19: 0.013 | H19: 0.013 | I19: 0.013 | J19: 0.013 | K19: 0.013 | L19: TCS is a services company, so it needs few physical assets (offices, computers). It spends about 0.9-1.4% of revenue on them (1.4% in FY26). We use 1.3%.
A20: PP&E depreciation (% of opening PP&E) | C20: =(B61-C91-C61)/B61 -> 0.27214292 | D20: =(C61-D91-D61)/C61 -> 0.24040475 | E20: =(D61-E91-E61)/D61 -> 0.12879342 | F20: =(E61-F91-F61)/E61 -> 0.20808049 | G20: 0.23 | H20: 0.23 | I20: 0.23 | J20: 0.23 | K20: 0.23 | L20: Assets like laptops and office fit-outs last about 4 years, so roughly 23% of their value is written off each year. History is 21-27%, apart from FY25 (13%), which was distorted by asset acquisitions.
A21: Intangible asset additions (% of revenue) | B21: =-B92/B41 -> 0.0025918625 | C21: =-C92/C41 -> 0.0015745726 | D21: =-D92/D41 -> 0.0018348395 | E21: =-E92/E41 -> 0.0036972631 | F21: =-F92/F41 -> 0.0013744237 | G21: 0.002 | H21: 0.002 | I21: 0.002 | J21: 0.002 | K21: 0.002 | L21: Mostly software licences. TCS spends about 0.2% of revenue on them (0.14-0.37% in FY23-26).
A22: Intangible amortisation (% of opening intangibles + additions) | C22: =(B64-C92-C64)/(B64-C92) -> 0.40453297 | D22: =(C64-D92-D64)/(C64-D92) -> 0.61038961 | E22: =(D64-E92-E64)/(D64-E92) -> 0.35350757 | F22: =(E64-F92-F64)/(E64-F92) -> 0.86534047 | G22: 0.5 | H22: 0.5 | I22: 0.5 | J22: 0.5 | K22: 0.5 | L22: Software is written off fast - about 2 years. History ranges 35-87% of the opening balance plus additions (average about 56%). We use 50%.
A23: New leases (% of revenue) | C23: =(C71-B71-C99)/C41 -> 0.006143051 | D23: =(D71-C71-D99)/D41 -> 0.0080824266 | E23: =(E71-D71-E99)/E41 -> 0.011886857 | F23: =(F71-E71-F99)/F41 -> 0.014051329 | G23: 0.012 | H23: 0.012 | I23: 0.012 | J23: 0.012 | K23: 0.012 | L23: TCS rents most of its offices. New lease contracts rose from 0.6% to 1.4% of revenue as offices expanded; we assume 1.2%.
A24: ROU depreciation (% of opening ROU assets) | C24: =(B62+C71-B71-C99-C62)/B62 -> 0.19133054 | D24: =(C62+D71-C71-D99-D62)/C62 -> 0.21441799 | E24: =(D62+E71-D71-E99-E62)/D62 -> 0.20872432 | F24: =(E62+F71-E71-F99-F62)/E62 -> 0.21563342 | G24: 0.21 | H24: 0.21 | I24: 0.21 | J24: 0.21 | K24: 0.21 | L24: Office leases last about 5 years, so about 21% of the leased-asset value is written off each year - in line with history (19-22%).
A25: Acquisitions (₹ crore) | B25: =-B94 -> 0 | C25: =-C94 -> 0 | D25: =-D94 -> 0 | E25: =-E94 -> 1063 | F25: =-F94 -> 7554 | G25: 0 | H25: 0 | I25: 0 | J25: 0 | K25: 0 | L25: Acquisitions are lumpy and hard to predict (zero in FY22-24, ₹7,554 crore in FY26), so we assume none.
A26: Working capital and investments
A27: Trade receivable days (on revenue) | B27: =B66/B41*365 -> 79.58452 | C27: =C66/C41*365 -> 80.87187 | D27: =D66/D41*365 -> 81.179632 | E27: =E66/E41*365 -> 84.409574 | F27: =F66/F41*365 -> 92.560548 | G27: 88 | H27: 87 | I27: 86 | J27: 86 | K27: 86 | L27: TCS takes about 86 days on average (last 3 years) to collect cash from clients. It slipped to 93 days in FY26. We assume it slowly improves back to 86.
A28: Trade payable days (on cost of revenue + other opex) | B28: =B73/(B42+B44)*365 -> 21.171511 | C28: =C73/(C42+C44)*365 -> 23.092648 | D28: =D73/(D42+D44)*365 -> 20.517952 | E28: =E73/(E42+E44)*365 -> 27.016103 | F28: =F73/(F42+F44)*365 -> 27.140081 | G28: 25 | H28: 25 | I28: 25 | J28: 25 | K28: 25 | L28: TCS pays its suppliers in about 20-27 days. We use 25 days, close to the recent average.
A29: Unearned and deferred revenue (% of revenue) | B29: =B74/B41 -> 0.01895658 | C29: =C74/C41 -> 0.017045303 | D29: =D74/D41 -> 0.015110443 | E29: =E74/E41 -> 0.015776034 | F29: =F74/F41 -> 0.016803922 | G29: 0.0165 | H29: 0.0165 | I29: 0.0165 | J29: 0.0165 | K29: 0.0165 | L29: Clients sometimes pay before the work is done. This advance money has averaged about 1.7% of revenue. We use 1.65%.
A30: Other assets (% of revenue) | B30: =B68/B41 -> 0.14860185 | C30: =C68/C41 -> 0.10535443 | D30: =D68/D41 -> 0.11065494 | E30: =E68/E41 -> 0.11576272 | F30: =F68/F41 -> 0.12640953 | G30: 0.12 | H30: 0.12 | I30: 0.12 | J30: 0.12 | K30: 0.12 | L30: Smaller items such as tax refunds due, deposits and prepaid expenses. These have averaged about 12% of revenue over the last 3 years.
A31: Other liabilities (% of revenue) | B31: =B75/B41 -> 0.16776703 | C31: =C75/C41 -> 0.13483221 | D31: =D75/D41 -> 0.13901608 | E31: =E75/E41 -> 0.1430692 | F31: =F75/F41 -> 0.16221945 | G31: 0.15 | H31: 0.15 | I31: 0.15 | J31: 0.15 | K31: 0.15 | L31: Smaller items such as tax owed, employee dues and provisions. These have averaged about 15% of revenue over the last 3 years.
A32: Investments and bank deposits (% of revenue) | B32: =B65/B41 -> 0.18887742 | C32: =C65/C41 -> 0.1821714 | D32: =D65/D41 -> 0.14957678 | E32: =E65/E41 -> 0.14916342 | F32: =F65/F41 -> 0.15159482 | G32: 0.15 | H32: 0.15 | I32: 0.15 | J32: 0.15 | K32: 0.15 | L32: TCS has kept investments and bank deposits at about 15% of revenue for the last 3 years (14.9-15.2%). We keep 15%, so the portfolio grows with the business.
A33: Leases, borrowings, finance costs and dividends
A34: Finance cost rate (% of average lease liabilities) | C34: =C50/AVERAGE(C71,B71) -> 0.10047723 | D34: =D50/AVERAGE(D71,C71) -> 0.099051499 | E34: =E50/AVERAGE(E71,D71) -> 0.091425946 | F34: =F50/AVERAGE(F71,E71) -> 0.11869407 | G34: 0.105 | H34: 0.105 | I34: 0.105 | J34: 0.105 | K34: 0.105 | L34: Historical figure = total finance costs / average lease liabilities, so it is a blended rate (it also includes other finance costs): 9-12%. For the forecast, 10.5% is our own assumption for lease finance cost.
A35: Lease principal repaid (% of opening lease liabilities) | C35: =-C99/B71 -> 0.19378358 | D35: =-D99/C71 -> 0.20993757 | E35: =-E99/D71 -> 0.20745543 | F35: =-F99/E71 -> 0.19814736 | G35: 0.2 | H35: 0.2 | I35: 0.2 | J35: 0.2 | K35: 0.2 | L35: TCS pays off about 20% of what it owes on leases every year (19-21% historically). We keep 20%.
A36: New borrowings / (repayments) (₹ crore) | B36: =B101 -> 0 | C36: =C101 -> 0 | D36: =D101 -> 0 | E36: =E101 -> 0 | F36: =F101 -> 0 | G36: 0 | H36: 0 | I36: 0 | J36: 0 | K36: 0 | L36: TCS has no loans and does not need any, so we assume zero.
A37: Interest rate on borrowings (on average balance) | G37: 0.085 | H37: 0.085 | I37: 0.085 | J37: 0.085 | K37: 0.085 | L37: Only used if you add borrowings above. 8.5% is an illustrative loan rate, charged on the average balance so new loans pay interest in the year they are taken.
A38: Dividend payout (% of profit attributable) | B38: =-B97/B55 -> 0.3489707 | C38: =-C97/C55 -> 0.98251358 | D38: =-D97/D55 -> 0.54931602 | E38: =-E97/E55 -> 0.92603959 | F38: =-F97/F55 -> 0.80412518 | G38: 0.85 | H38: 0.85 | I38: 0.85 | J38: 0.85 | K38: 0.85 | L38: TCS gives most of its profit back to shareholders as dividends - 80-93% in the last two years. We use 85% and assume no buy-backs.
A40: INCOME STATEMENT
A41: Revenue from operations | B41: 191754 | C41: 225458 | D41: 240893 | E41: 255324 | F41: 267021 | G41: =F41*(1+G10) -> 280372.05 | H41: =G41*(1+H10) -> 295792.51 | I41: =H41*(1+I10) -> 313540.06 | J41: =I41*(1+J10) -> 332352.47 | K41: =J41*(1+K10) -> 352293.62
A42: Cost of revenue | B42: 108717 | C42: 129403 | D42: 143833 | E42: 157436 | F42: 159393 | G42: =G41*G11 -> 168223.23 | H42: =H41*H11 -> 177475.51 | I42: =I41*I11 -> 188124.04 | J42: =J41*J11 -> 199411.48 | K42: =K41*K11 -> 211376.17
A43: Gross profit | B43: =B41-B42 -> 83037 | C43: =C41-C42 -> 96055 | D43: =D41-D42 -> 97060 | E43: =E41-E42 -> 97888 | F43: =F41-F42 -> 107628 | G43: =G41-G42 -> 112148.82 | H43: =H41-H42 -> 118317.01 | I43: =I41-I42 -> 125416.03 | ... K43: =K41-K42 -> 140917.45
A44: Other operating expenses | B44: 29980 | C44: 36796 | D44: 33722 | E44: 30481 | F44: 39756 | G44: =G41*G12 -> 36448.366 | H44: =H41*H12 -> 38453.027 | I44: =I41*I12 -> 40760.208 | J44: =J41*J12 -> 43205.821 | K44: =K41*K12 -> 45798.17
A45: EBITDA | B45: =B43-B44 -> 53057 | C45: =C43-C44 -> 59259 | D45: =D43-D44 -> 63338 | E45: =E43-E44 -> 67407 | F45: =F43-F44 -> 67872 | G45: =G43-G44 -> 75700.454 | H45: =H43-H44 -> 79863.978 | I45: =I43-I44 -> 84655.817 | ... K45: =K43-K44 -> 95119.276
A46: Depreciation and amortisation | B46: 4604 | C46: 5022 | D46: 4985 | E46: 5242 | F46: 5560 | G46: =G126 -> 5834.352 | H46: =H126 -> 6279.9465 | I46: =I126 -> 6700.0398 | J46: =J126 -> 7124.5114 | K46: =K126 -> 7564.2008
A47: EBIT | B47: =B45-B46 -> 48453 | C47: =C45-C46 -> 54237 | D47: =D45-D46 -> 58353 | E47: =E45-E46 -> 62165 | F47: =F45-F46 -> 62312 | G47: =G45-G46 -> 69866.101 | H47: =H45-H46 -> 73584.032 | I47: =I45-I46 -> 77955.777 | ... K47: =K45-K46 -> 87555.075
A48: Interest income | B48: 2663 | C48: 3248 | D48: 3781 | E48: 3296 | F48: 3854 | G48: =(F67+F65)*G13 -> 3517.2 | H48: =(G67+G65)*H13 -> 3970.4303 | I48: =(H67+H65)*I13 -> 4478.1666 | J48: =(I67+I65)*J13 -> 5004.8227 | K48: =(J67+J65)*K13 -> 5498.2187
A49: Other non-interest income | B49: 1355 | C49: 201 | D49: 641 | E49: 666 | F49: 548 | G49: =G41*G14 -> 560.7441 | H49: =H41*H14 -> 591.58503 | I49: =I41*I14 -> 627.08013 | J49: =J41*J14 -> 664.70493 | K49: =K41*K14 -> 704.58723
A50: Finance costs (mainly interest on leases) | B50: 784 | C50: 779 | D50: 778 | E50: 796 | F50: 1227 | G50: =G147 -> 1242.8779 | H50: =H147 -> 1357.286 | I50: =I147 -> 1469.7083 | J50: =J147 -> 1582.6789 | K50: =K147 -> 1697.4702
A51: Profit before tax | B51: =B47+B48+B49-B50 -> 51687 | C51: =C47+C48+C49-C50 -> 56907 | D51: =D47+D48+D49-D50 -> 61997 | E51: =E47+E48+E49-E50 -> 65331 | F51: =F47+F48+F49-F50 -> 65487 | G51: =G47+G48+G49-G50 -> 72701.168 | H51: =H47+H48+H49-H50 -> 76788.761 | I51: =I47+I48+I49-I50 -> 81591.316 | ... K51: =K47+K48+K49-K50 -> 92060.411
A52: Tax expense | B52: 13238 | C52: 14604 | D52: 15898 | E52: 16534 | F52: 16033 | G52: =G51*G15 -> 18538.798 | H52: =H51*H15 -> 19581.134 | I52: =I51*I15 -> 20805.786 | J52: =J51*J15 -> 22107.863 | K52: =K51*K15 -> 23475.405
A53: Profit for the year | B53: =B51-B52 -> 38449 | C53: =C51-C52 -> 42303 | D53: =D51-D52 -> 46099 | E53: =E51-E52 -> 48797 | F53: =F51-F52 -> 49454 | G53: =G51-G52 -> 54162.37 | H53: =H51-H52 -> 57207.627 | I53: =I51-I52 -> 60785.53 | ... K53: =K51-K52 -> 68585.006
A54: Less: Non-controlling interests | B54: 122 | C54: 156 | D54: 191 | E54: 244 | F54: 244 | G54: =G53*G16 -> 270.81185 | H54: =H53*H16 -> 286.03814 | I54: =I53*I16 -> 303.92765 | J54: =J53*J16 -> 322.9482 | K54: =K53*K16 -> 342.92503
A55: Profit attributable to shareholders | B55: =B53-B54 -> 38327 | C55: =C53-C54 -> 42147 | D55: =D53-D54 -> 45908 | E55: =E53-E54 -> 48553 | F55: =F53-F54 -> 49210 | G55: =G53-G54 -> 53891.558 | H55: =H53-H54 -> 56921.589 | I55: =I53-I54 -> 60481.603 | ... K55: =K53-K54 -> 68242.081
A56: Weighted average shares (crore) | B56: 369.88322 | C56: 365.90514 | D56: 364.68518 | E56: 361.80875 | F56: 361.80875 | G56: =G17 -> 361.80875 | H56: =H17 -> 361.80875 | I56: =I17 -> 361.80875 | J56: =J17 -> 361.80875 | K56: =K17 -> 361.80875
A57: EPS - basic and diluted (₹) | B57: =B55/B56 -> 103.61919 | C57: =C55/C56 -> 115.18559 | D57: =D55/D56 -> 125.88392 | E57: =E55/E56 -> 134.19521 | F57: =F55/F56 -> 136.01108 | G57: =G55/G56 -> 148.9504 | H57: =H55/H56 -> 157.32507 | I57: =I55/I56 -> 167.16457 | ... K57: =K55/K56 -> 188.61368
A59: BALANCE SHEET
A60: Assets
A61: Property, plant and equipment (including CWIP) | B61: 11979 | C61: 11464 | D61: 10940 | E61: 12524 | F61: 13697 | G61: =G115 -> 14191.527 | H61: =H115 -> 14772.778 | I61: =I115 -> 15451.06 | J61: =J115 -> 16217.898 | K61: =K115 -> 17067.599
A62: Right-of-use assets | B62: 7636 | C62: 7560 | D62: 7886 | E62: 9275 | F62: 11027 | G62: =G120 -> 12075.795 | H62: =H120 -> 13089.388 | I62: =I120 -> 14103.097 | J62: =J120 -> 15129.676 | K62: =K120 -> 16179.968
A63: Goodwill | B63: 1787 | C63: 1858 | D63: 1832 | E63: 1860 | F63: 9108 | G63: =F63+G25 -> 9108 | H63: =G63+H25 -> 9108 | I63: =H63+I25 -> 9108 | J63: =I63+J25 -> 9108 | K63: =J63+K25 -> 9108
A64: Other intangible assets | B64: 1101 | C64: 867 | D64: 510 | E64: 940 | F64: 176 | G64: =G125 -> 368.37205 | H64: =H125 -> 479.97854 | I64: =I125 -> 553.52933 | J64: =J125 -> 609.11713 | K64: =K125 -> 656.85218
A65: Investments and bank deposits | B65: 36218 | C65: 41072 | D65: 36032 | E65: 38085 | F65: 40479 | G65: =G41*G32 -> 42055.807 | H65: =H41*H32 -> 44368.877 | I65: =I41*I32 -> 47031.01 | J65: =J41*J32 -> 49852.87 | K65: =K41*K32 -> 52844.042
A66: Trade receivables | B66: 41810 | C66: 49954 | D66: 53577 | E66: 59046 | F66: 67714 | G66: =G129 -> 67596.549 | H66: =H129 -> 70503.969 | I66: =I129 -> 73875.193 | J66: =J129 -> 78307.705 | K66: =K129 -> 83006.167
A67: Cash and cash equivalents | B67: 12488 | C67: 7123 | D67: 9016 | E67: 8342 | F67: 6417 | G67: =G107 -> 10883.263 | H67: =H107 -> 15340.011 | I67: =I107 -> 19699.959 | J67: =J107 -> 23456.712 | K67: =K107 -> 27427.627
A68: Other assets | B68: 28495 | C68: 23753 | D68: 26656 | E68: 29557 | F68: 33754 | G68: =G130 -> 33644.646 | H68: =H130 -> 35495.102 | I68: =I130 -> 37624.808 | J68: =J130 -> 39882.296 | K68: =K130 -> 42275.234
A69: TOTAL ASSETS | B69: =SUM(B61:B68) -> 141514 | C69: =SUM(C61:C68) -> 143651 | D69: =SUM(D61:D68) -> 146449 | E69: =SUM(E61:E68) -> 159629 | F69: =SUM(F61:F68) -> 182372 | G69: =SUM(G61:G68) -> 189923.96 | H69: =SUM(H61:H68) -> 203158.1 | I69: =SUM(I61:I68) -> 217446.66 | ... K69: =SUM(K61:K68) -> 248565.49
A70: Liabilities and equity
A71: Lease liabilities | B71: 7818 | C71: 7688 | D71: 8021 | E71: 9392 | F71: 11283 | G71: =G141 -> 12390.865 | H71: =H141 -> 13462.202 | I71: =I141 -> 14532.242 | J71: =J141 -> 15614.023 | K71: =K141 -> 16718.742
A72: Borrowings | B72: 0 | C72: 0 | D72: 0 | E72: 0 | F72: 0 | G72: =G144 -> 0 | H72: =H144 -> 0 | I72: =I144 -> 0 | J72: =J144 -> 0 | K72: =K144 -> 0
A73: Trade payables | B73: 8045 | C73: 10515 | D73: 9981 | E73: 13909 | F73: 14808 | G73: =G131 -> 14018.602 | H73: =H131 -> 14789.626 | I73: =I131 -> 15677.003 | J73: =J131 -> 16617.623 | K73: =K131 -> 17614.681
A74: Unearned and deferred revenue | B74: 3635 | C74: 3843 | D74: 3640 | E74: 4028 | F74: 4487 | G74: =G132 -> 4626.1388 | H74: =H132 -> 4880.5765 | I74: =I132 -> 5173.411 | J74: =J132 -> 5483.8157 | K74: =K132 -> 5812.8447
A75: Other liabilities | B75: 32170 | C75: 30399 | D75: 33488 | E75: 36529 | F75: 43316 | G75: =G133 -> 42055.807 | H75: =H133 -> 44368.877 | I75: =I133 -> 47031.01 | J75: =J133 -> 49852.87 | K75: =K133 -> 52844.042
A76: Total liabilities | B76: =SUM(B71:B75) -> 51668 | C76: =SUM(C71:C75) -> 52445 | D76: =SUM(D71:D75) -> 55130 | E76: =SUM(E71:E75) -> 63858 | F76: =SUM(F71:F75) -> 73894 | G76: =SUM(G71:G75) -> 73091.413 | H76: =SUM(H71:H75) -> 77501.281 | I76: =SUM(I71:I75) -> 82413.666 | ... K76: =SUM(K71:K75) -> 92990.31
A77: Shareholders' equity | B77: 89139 | C77: 90424 | D77: 90489 | E77: 94756 | F77: 107240 | G77: =F77+G55+G97+G98 -> 115323.73 | H77: =G77+H55+H97+H98 -> 123861.97 | I77: =H77+I55+I97+I98 -> 132934.21 | J77: =I77+J55+J97+J98 -> 142574.22 | K77: =J77+K55+K97+K98 -> 152810.53
A78: Non-controlling interests | B78: 707 | C78: 782 | D78: 830 | E78: 1015 | F78: 1238 | G78: =F78+G54 -> 1508.8118 | H78: =G78+H54 -> 1794.85 | I78: =H78+I54 -> 2098.7776 | J78: =I78+J54 -> 2421.7258 | K78: =J78+K54 -> 2764.6509
A79: Total equity | B79: =B77+B78 -> 89846 | C79: =C77+C78 -> 91206 | D79: =D77+D78 -> 91319 | E79: =E77+E78 -> 95771 | F79: =F77+F78 -> 108478 | G79: =G77+G78 -> 116832.55 | H79: =H77+H78 -> 125656.82 | I79: =I77+I78 -> 135032.99 | ... K79: =K77+K78 -> 155575.18
A80: TOTAL LIABILITIES AND EQUITY | B80: =B76+B79 -> 141514 | C80: =C76+C79 -> 143651 | D80: =D76+D79 -> 146449 | E80: =E76+E79 -> 159629 | F80: =F76+F79 -> 182372 | G80: =G76+G79 -> 189923.96 | H80: =H76+H79 -> 203158.1 | I80: =I76+I79 -> 217446.66 | ... K80: =K76+K79 -> 248565.49
A81: Check (should be 0) | B81: =ROUND(B69-B80,3) -> 0 | C81: =ROUND(C69-C80,3) -> 0 | D81: =ROUND(D69-D80,3) -> 0 | E81: =ROUND(E69-E80,3) -> 0 | F81: =ROUND(F69-F80,3) -> 0 | G81: =ROUND(G69-G80,3) -> 0 | H81: =ROUND(H69-H80,3) -> 0 | I81: =ROUND(I69-I80,3) -> 0 | ... K81: =ROUND(K69-K80,3) -> 0
A83: CASH FLOW STATEMENT
A84: Profit for the year | B84: =B53 -> 38449 | C84: =C53 -> 42303 | D84: =D53 -> 46099 | E84: =E53 -> 48797 | F84: =F53 -> 49454 | G84: =G53 -> 54162.37 | H84: =H53 -> 57207.627 | I84: =I53 -> 60785.53 | ... K84: =K53 -> 68585.006
A85: Add: Depreciation and amortisation | B85: =B46 -> 4604 | C85: =C46 -> 5022 | D85: =D46 -> 4985 | E85: =E46 -> 5242 | F85: =F46 -> 5560 | G85: =G46 -> 5834.352 | H85: =H46 -> 6279.9465 | I85: =I46 -> 6700.0398 | ... K85: =K46 -> 7564.2008
A86: Add: Finance costs | B86: =B50 -> 784 | C86: =C50 -> 779 | D86: =D50 -> 778 | E86: =E50 -> 796 | F86: =F50 -> 1227 | G86: =G50 -> 1242.8779 | H86: =H50 -> 1357.286 | I86: =I50 -> 1469.7083 | ... K86: =K50 -> 1697.4702
A87: Change in working capital | B87: -2769 | C87: -4217 | D87: -6882 | E87: -3359 | F87: -2210 | G87: =-G135 -> -1683.6462 | H87: =-H135 -> -1419.3451 | I87: =-I135 -> -1658.5856 | J87: =-J135 -> -2617.1146 | K87: =-K135 -> -2774.1415
A88: Less: Interest income (shown in investing) | B88: -2663 | C88: -3248 | D88: -3781 | E88: -3296 | F88: -3854 | G88: =-G48 -> -3517.2 | H88: =-H48 -> -3970.4303 | I88: =-I48 -> -4478.1666 | J88: =-J48 -> -5004.8227 | K88: =-K48 -> -5498.2187
A89: Other operating items (taxes, non-cash) | B89: 1544 | C89: 1326 | D89: 3139 | E89: 728 | F89: 1917 | G89: 0 | H89: 0 | I89: 0 | J89: 0 | K89: 0
A90: Cash from operations (CFO) | B90: =SUM(B84:B89) -> 39949 | C90: =SUM(C84:C89) -> 41965 | D90: =SUM(D84:D89) -> 44338 | E90: =SUM(E84:E89) -> 48908 | F90: =SUM(F84:F89) -> 52094 | G90: =SUM(G84:G89) -> 56038.754 | H90: =SUM(H84:H89) -> 59455.084 | I90: =SUM(I84:I89) -> 62818.526 | ... K90: =SUM(K84:K89) -> 69574.317
A91: Capex - property, plant and equipment | B91: -2498 | C91: -2745 | D91: -2232 | E91: -2993 | F91: -3779 | G91: =-G113 -> -3644.8366 | H91: =-H113 -> -3845.3027 | I91: =-I113 -> -4076.0208 | J91: =-J113 -> -4320.5821 | K91: =-K113 -> -4579.817
A92: Purchase of intangible assets | B92: -497 | C92: -355 | D92: -442 | E92: -944 | F92: -367 | G92: =-G123 -> -560.7441 | H92: =-H123 -> -591.58503 | I92: =-I123 -> -627.08013 | J92: =-J123 -> -664.70493 | K92: =-K123 -> -704.58723
A93: Net investments and deposits | B93: -640 | C93: 7 | D93: 5657 | E93: -416 | F93: -4293 | G93: =-(G65-F65) -> -1576.8075 | H93: =-(H65-G65) -> -2313.0694 | I93: =-(I65-H65) -> -2662.1326 | J93: =-(J65-I65) -> -2821.8606 | K93: =-(K65-J65) -> -2991.1722
A94: Acquisitions | B94: 0 | C94: 0 | D94: 0 | E94: -1063 | F94: -7554 | G94: =-G25 -> 0 | H94: =-H25 -> 0 | I94: =-I25 -> 0 | J94: =-J25 -> 0 | K94: =-K25 -> 0
A95: Interest received (and other investing) | B95: 2738 | C95: 3132 | D95: 3043 | E95: 3098 | F95: 3148 | G95: =G48 -> 3517.2 | H95: =H48 -> 3970.4303 | I95: =I48 -> 4478.1666 | J95: =J48 -> 5004.8227 | K95: =K48 -> 5498.2187
A96: Cash from investing (CFI) | B96: =SUM(B91:B95) -> -897 | C96: =SUM(C91:C95) -> 39 | D96: =SUM(D91:D95) -> 6026 | E96: =SUM(E91:E95) -> -2318 | F96: =SUM(F91:F95) -> -12845 | G96: =SUM(G91:G95) -> -2265.1882 | H96: =SUM(H91:H95) -> -2779.5268 | I96: =SUM(I91:I95) -> -2887.067 | ... K96: =SUM(K91:K95) -> -2777.3578
A97: Dividends paid | B97: -13375 | C97: -41410 | D97: -25218 | E97: -44962 | F97: -39571 | G97: =-G55*G38 -> -45807.824 | H97: =-H55*H38 -> -48383.351 | I97: =-I55*I38 -> -51409.362 | J97: =-J55*J38 -> -54626.688 | K97: =-K55*K38 -> -58005.769
A98: Share buy-back | B98: -18067 | C98: -4174 | D98: -21005 | E98: 0 | F98: 0 | G98: 0 | H98: 0 | I98: 0 | J98: 0 | K98: 0
A99: Repayment of lease liabilities | B99: -1417 | C99: -1515 | D99: -1614 | E99: -1664 | F99: -1861 | G99: =-G140 -> -2256.6 | H99: =-H140 -> -2478.1729 | I99: =-I140 -> -2692.4404 | J99: =-J140 -> -2906.4484 | K99: =-K140 -> -3122.8047
A100: Interest paid | B100: -698 | C100: -779 | D100: -699 | E100: -840 | F100: -901 | G100: =-G50 -> -1242.8779 | H100: =-H50 -> -1357.286 | I100: =-I50 -> -1469.7083 | J100: =-J50 -> -1582.6789 | K100: =-K50 -> -1697.4702
A101: Borrowings drawn / (repaid) | B101: 0 | C101: 0 | D101: 0 | E101: 0 | F101: 0 | G101: =G143 -> 0 | H101: =H143 -> 0 | I101: =I143 -> 0 | J101: =J143 -> 0 | K101: =K143 -> 0
A102: Other financing | B102: -24 | C102: 0 | D102: 0 | E102: 28 | F102: 200 | G102: 0 | H102: 0 | I102: 0 | J102: 0 | K102: 0
A103: Cash from financing (CFF) | B103: =SUM(B97:B102) -> -33581 | C103: =SUM(C97:C102) -> -47878 | D103: =SUM(D97:D102) -> -48536 | E103: =SUM(E97:E102) -> -47438 | F103: =SUM(F97:F102) -> -42133 | G103: =SUM(G97:G102) -> -49307.302 | H103: =SUM(H97:H102) -> -52218.81 | I103: =SUM(I97:I102) -> -55571.511 | ... K103: =SUM(K97:K102) -> -62826.044
A104: Net change in cash | B104: =B90+B96+B103 -> 5471 | C104: =C90+C96+C103 -> -5874 | D104: =D90+D96+D103 -> 1828 | E104: =E90+E96+E103 -> -848 | F104: =F90+F96+F103 -> -2884 | G104: =G90+G96+G103 -> 4466.2631 | H104: =H90+H96+H103 -> 4456.7479 | I104: =I90+I96+I103 -> 4359.9483 | ... K104: =K90+K96+K103 -> 3970.9154
A105: Opening cash | B105: 6858 | C105: 12488 | D105: 7123 | E105: 9016 | F105: 8342 | G105: =F107 -> 6417 | H105: =G107 -> 10883.263 | I105: =H107 -> 15340.011 | J105: =I107 -> 19699.959 | K105: =J107 -> 23456.712
A106: FX difference | B106: 159 | C106: 509 | D106: 65 | E106: 174 | F106: 959 | G106: 0 | H106: 0 | I106: 0 | J106: 0 | K106: 0
A107: Closing cash | B107: =B105+B104+B106 -> 12488 | C107: =C105+C104+C106 -> 7123 | D107: =D105+D104+D106 -> 9016 | E107: =E105+E104+E106 -> 8342 | F107: =F105+F104+F106 -> 6417 | G107: =G105+G104+G106 -> 10883.263 | H107: =H105+H104+H106 -> 15340.011 | I107: =I105+I104+I106 -> 19699.959 | ... K107: =K105+K104+K106 -> 27427.627
...

Sheet Summary & Charts
A1: TCS - Summary and Charts
A2: ₹ crore unless stated.
A4: Key metrics | B4: FY22A | C4: FY23A | D4: FY24A | E4: FY25A | F4: FY26A | G4: FY27E | H4: FY28E | I4: FY29E | J4: FY30E | K4: FY31E
A5: Revenue | B5: =Model!B41 -> 191754 | C5: =Model!C41 -> 225458 | D5: =Model!D41 -> 240893 | E5: =Model!E41 -> 255324 | F5: =Model!F41 -> 267021 | G5: =Model!G41 -> 280372.05 | H5: =Model!H41 -> 295792.51 | I5: =Model!I41 -> 313540.06 | ... K5: =Model!K41 -> 352293.62
A6: Revenue growth | C6: =Model!C41/Model!B41-1 -> 0.17576687 | D6: =Model!D41/Model!C41-1 -> 0.068460645 | E6: =Model!E41/Model!D41-1 -> 0.059906265 | F6: =Model!F41/Model!E41-1 -> 0.04581238 | G6: =Model!G41/Model!F41-1 -> 0.05 | H6: =Model!H41/Model!G41-1 -> 0.055 | I6: =Model!I41/Model!H41-1 -> 0.06 | J6: =Model!J41/Model!I41-1 -> 0.06 | K6: =Model!K41/Model!J41-1 -> 0.06
A7: EBITDA | B7: =Model!B45 -> 53057 | C7: =Model!C45 -> 59259 | D7: =Model!D45 -> 63338 | E7: =Model!E45 -> 67407 | F7: =Model!F45 -> 67872 | G7: =Model!G45 -> 75700.454 | H7: =Model!H45 -> 79863.978 | I7: =Model!I45 -> 84655.817 | ... K7: =Model!K45 -> 95119.276
A8: EBITDA margin | B8: =Model!B45/Model!B41 -> 0.27669305 | C8: =Model!C45/Model!C41 -> 0.26283831 | D8: =Model!D45/Model!D41 -> 0.26293001 | E8: =Model!E45/Model!E41 -> 0.26400573 | F8: =Model!F45/Model!F41 -> 0.25418226 | G8: =Model!G45/Model!G41 -> 0.27 | H8: =Model!H45/Model!H41 -> 0.27 | I8: =Model!I45/Model!I41 -> 0.27 | ... K8: =Model!K45/Model!K41 -> 0.27
A9: Profit attributable to shareholders | B9: =Model!B55 -> 38327 | C9: =Model!C55 -> 42147 | D9: =Model!D55 -> 45908 | E9: =Model!E55 -> 48553 | F9: =Model!F55 -> 49210 | G9: =Model!G55 -> 53891.558 | H9: =Model!H55 -> 56921.589 | I9: =Model!I55 -> 60481.603 | ... K9: =Model!K55 -> 68242.081
A10: Net profit margin | B10: =Model!B55/Model!B41 -> 0.19987588 | C10: =Model!C55/Model!C41 -> 0.18693947 | D10: =Model!D55/Model!D41 -> 0.19057424 | E10: =Model!E55/Model!E41 -> 0.1901623 | F10: =Model!F55/Model!F41 -> 0.18429262 | G10: =Model!G55/Model!G41 -> 0.19221445 | H10: =Model!H55/Model!H41 -> 0.19243756 | I10: =Model!I55/Model!I41 -> 0.19289912 | ... K10: =Model!K55/Model!K41 -> 0.19370797
A11: EPS (₹) | B11: =Model!B57 -> 103.61919 | C11: =Model!C57 -> 115.18559 | D11: =Model!D57 -> 125.88392 | E11: =Model!E57 -> 134.19521 | F11: =Model!F57 -> 136.01108 | G11: =Model!G57 -> 148.9504 | H11: =Model!H57 -> 157.32507 | I11: =Model!I57 -> 167.16457 | ... K11: =Model!K57 -> 188.61368
A12: Cash from operations | B12: =Model!B90 -> 39949 | C12: =Model!C90 -> 41965 | D12: =Model!D90 -> 44338 | E12: =Model!E90 -> 48908 | F12: =Model!F90 -> 52094 | G12: =Model!G90 -> 56038.754 | H12: =Model!H90 -> 59455.084 | I12: =Model!I90 -> 62818.526 | ... K12: =Model!K90 -> 69574.317
A13: Capex (PP&E + intangibles) | B13: =-(Model!B91+Model!B92) -> 2995 | C13: =-(Model!C91+Model!C92) -> 3100 | D13: =-(Model!D91+Model!D92) -> 2674 | E13: =-(Model!E91+Model!E92) -> 3937 | F13: =-(Model!F91+Model!F92) -> 4146 | G13: =-(Model!G91+Model!G92) -> 4205.5808 | H13: =-(Model!H91+Model!H92) -> 4436.8877 | I13: =-(Model!I91+Model!I92) -> 4703.101 | ... K13: =-(Model!K91+Model!K92) -> 5284.4042
A14: Free cash flow (CFO - capex) | B14: =Model!B90+Model!B91+Model!B92 -> 36954 | C14: =Model!C90+Model!C91+Model!C92 -> 38865 | D14: =Model!D90+Model!D91+Model!D92 -> 41664 | E14: =Model!E90+Model!E91+Model!E92 -> 44971 | F14: =Model!F90+Model!F91+Model!F92 -> 47948 | G14: =Model!G90+Model!G91+Model!G92 -> 51833.173 | H14: =Model!H90+Model!H91+Model!H92 -> 55018.197 | I14: =Model!I90+Model!I91+Model!I92 -> 58115.425 | ... K14: =Model!K90+Model!K91+Model!K92 -> 64289.913
A15: Dividends paid | B15: =-Model!B97 -> 13375 | C15: =-Model!C97 -> 41410 | D15: =-Model!D97 -> 25218 | E15: =-Model!E97 -> 44962 | F15: =-Model!F97 -> 39571 | G15: =-Model!G97 -> 45807.824 | H15: =-Model!H97 -> 48383.351 | I15: =-Model!I97 -> 51409.362 | ... K15: =-Model!K97 -> 58005.769
A16: Closing cash | B16: =Model!B67 -> 12488 | C16: =Model!C67 -> 7123 | D16: =Model!D67 -> 9016 | E16: =Model!E67 -> 8342 | F16: =Model!F67 -> 6417 | G16: =Model!G67 -> 10883.263 | H16: =Model!H67 -> 15340.011 | I16: =Model!I67 -> 19699.959 | ... K16: =Model!K67 -> 27427.627
A17: Total equity | B17: =Model!B79 -> 89846 | C17: =Model!C79 -> 91206 | D17: =Model!D79 -> 91319 | E17: =Model!E79 -> 95771 | F17: =Model!F79 -> 108478 | G17: =Model!G79 -> 116832.55 | H17: =Model!H79 -> 125656.82 | I17: =Model!I79 -> 135032.99 | ... K17: =Model!K79 -> 155575.18
A18: Return on equity | C18: =Model!C55/AVERAGE(Model!C77,Model!B77) -> 0.4694397 | D18: =Model!D55/AVERAGE(Model!D77,Model!C77) -> 0.50751466 | E18: =Model!E55/AVERAGE(Model!E77,Model!D77) -> 0.52420308 | F18: =Model!F55/AVERAGE(Model!F77,Model!E77) -> 0.48723737 | G18: =Model!G55/AVERAGE(Model!G77,Model!F77) -> 0.48427978 | H18: =Model!H55/AVERAGE(Model!H77,Model!G77) -> 0.47596146 | I18: =Model!I55/AVERAGE(Model!I77,Model!H77) -> 0.47104752 | J18: =Model!J55/AVERAGE(Model!J77,Model!I77) -> 0.46653158 | K18: =Model!K55/AVERAGE(Model!K77,Model!J77) -> 0.46205556
